LICENSE
MANIFEST.in
README.md
setup.py
tap_ms_teams/__init__.py
tap_ms_teams/catalog.py
tap_ms_teams/client.py
tap_ms_teams/streams.py
tap_ms_teams/transform.py
tap_ms_teams.egg-info/PKG-INFO
tap_ms_teams.egg-info/SOURCES.txt
tap_ms_teams.egg-info/dependency_links.txt
tap_ms_teams.egg-info/entry_points.txt
tap_ms_teams.egg-info/requires.txt
tap_ms_teams.egg-info/top_level.txt
tap_ms_teams/schemas/channel.json
tap_ms_teams/schemas/channel_members.json
tap_ms_teams/schemas/channel_message_replies.json
tap_ms_teams/schemas/channel_messages.json
tap_ms_teams/schemas/channel_tabs.json
tap_ms_teams/schemas/channels.json
tap_ms_teams/schemas/conversation_posts.json
tap_ms_teams/schemas/conversation_threads.json
tap_ms_teams/schemas/conversations.json
tap_ms_teams/schemas/group_members.json
tap_ms_teams/schemas/group_owners.json
tap_ms_teams/schemas/groups.json
tap_ms_teams/schemas/team_device_usage_report.json
tap_ms_teams/schemas/team_drives.json
tap_ms_teams/schemas/users.json