Metadata-Version: 2.1
Name: tap-ms-teams
Version: 0.0.2
Summary: Singer.io tap for extracting data from the Microsofts Teams Graph API
Home-page: UNKNOWN
Author: scott.coleman@bytecode.io
License: UNKNOWN
Platform: UNKNOWN
Classifier: Programming Language :: Python :: 3 :: Only
Requires-Python: >=3.5.2
Provides-Extra: dev
